bigtree_sso/__init__.py
bigtree_sso/encryp.py
bigtree_sso/urls.py
bigtree_sso/views.py
bigtree_sso-0.0.3.dist-info/DESCRIPTION.rst
bigtree_sso-0.0.3.dist-info/METADATA
bigtree_sso-0.0.3.dist-info/RECORD
bigtree_sso-0.0.3.dist-info/WHEEL
bigtree_sso-0.0.3.dist-info/metadata.json
bigtree_sso-0.0.3.dist-info/top_level.txt
