Metadata-Version: 2.0
Name: bigtree-sso
Version: 0.0.3
Summary: bigtree sso. 
Home-page: http://www.hshl.ltd
Author: bigtiger
Author-email: chinafengheping@gmail.com
License: UNKNOWN
Platform: UNKNOWN
Requires-Dist: bigtree-api (>=0.0.1)
Requires-Dist: django (>=1.7.7)
Requires-Dist: django-restful (>=0.0.5)
Requires-Dist: pycrypto (>=2.6.1)
Requires-Dist: six
